quickhost_aws/AWSApp.py
quickhost_aws/AWSConfig.py
quickhost_aws/AWSHost.py
quickhost_aws/AWSIam.py
quickhost_aws/AWSKeypair.py
quickhost_aws/AWSNetworking.py
quickhost_aws/AWSResource.py
quickhost_aws/AWSSG.py
quickhost_aws/PluginArgs.py
quickhost_aws/__init__.py
quickhost_aws/constants.py
quickhost_aws/utilities.py
quickhost_aws-0.3.0.dist-info/METADATA
quickhost_aws-0.3.0.dist-info/WHEEL
quickhost_aws-0.3.0.dist-info/entry_points.txt
quickhost_aws-0.3.0.dist-info/top_level.txt
quickhost_aws-0.3.0.dist-info/RECORD
