Metadata-Version: 2.4
Name: quickhost-aws
Version: 0.3.0
Summary: quickhost plugin for AWS
Author-email: Michael Zborowski <mzborowski@yahoo.com>
Classifier: Programming Language :: Python :: 3
Classifier: License :: OSI Approved :: MIT License
Classifier: Operating System :: OS Independent
Requires-Python: >=3.10
Requires-Dist: boto3
Requires-Dist: cryptography
